flash/SSE.py
flash/__init__.py
flash/_callback.py
flash/_callback_context.py
flash/_class_callback.py
flash/_configs.py
flash/_event_callback.py
flash/_get_app.py
flash/_hooks.py
flash/_imports_.py
flash/_page_extension.py
flash/_pages.py
flash/_utils.py
flash/_validate.py
flash/_watch.py
flash/async-SSE.js
flash/background_callback/__init__.py
flash/background_callback/_proxy_set_props.py
flash/background_callback/managers/__init__.py
flash/background_callback/managers/celery_manager.py
flash/background_callback/managers/diskcache_manager.py
flash/flash.js
flash/flash.py
flash/metadata.json
flash/package-info.json
flash/proptypes.js
dash_flash-1.3.1.dist-info/METADATA
dash_flash-1.3.1.dist-info/WHEEL
dash_flash-1.3.1.dist-info/RECORD
