Metadata-Version: 2.3
Name: dash-flash
Version: 1.3.1
Summary: Flash - async port of the Dash framework
License: MIT
Author: chgiesse
Requires-Python: >=3.12,<4.0
Classifier: License :: OSI Approved :: MIT License
Classifier: Programming Language :: Python :: 3
Classifier: Programming Language :: Python :: 3.12
Classifier: Programming Language :: Python :: 3.13
Requires-Dist: Quart (>=0.20.0,<0.21.0)
Requires-Dist: dash (>=3.0.0rc1,<4.0.0)
Requires-Dist: quart-compress (>=0.2.1,<0.3.0)
Project-URL: Repository, https://github.com/chgiesse/flash
